{
	"miniprogramRoot": "miniprogram/",
	"cloudfunctionRoot": "cloudfunctions/",
	"setting": {
		"urlCheck": false,
		"es6": true,
		"enhance": true,
		"postcss": true,
		"minified": true,
		"newFeature": true,
		"coverView": true,
		"autoAudits": false,
		"showShadowRootInWxmlPanel": true,
		"scopeDataCheck": false,
		"checkInvalidKey": true,
		"checkSiteMap": true,
		"uploadWithSourceMap": true,
		"babelSetting": {
			"ignore": [],
			"disablePlugins": [],
			"outputPath": ""
		},
		"useCompilerModule": true,
		"userConfirmedUseCompilerModuleSwitch": false
	},
	"appid": "wxbc686226ccc443f1",
	"projectname": "YiShang-s",
	"libVersion": "2.11.2",
	"simulatorType": "wechat",
	"simulatorPluginLibVersion": {},
	"compileType": "miniprogram",
	"condition": {
		"search": {
			"current": -1,
			"list": []
		},
		"conversation": {
			"current": -1,
			"list": []
		},
		"plugin": {
			"current": -1,
			"list": []
		},
		"game": {
			"list": []
		},
		"gamePlugin": {
			"current": -1,
			"list": []
		},
		"miniprogram": {
			"current": -1,
			"list": [
				{
					"id": 0,
					"name": "pages/index/index",
					"pathName": "pages/index/index",
					"query": "",
					"scene": null
				},
				{
					"id": -1,
					"name": "pagesCustomer/index/index",
					"pathName": "pagesCustomer/index/index",
					"query": "",
					"scene": null
				},
				{
					"id": -1,
					"name": "pages/payAndDelivery/ordersList/ordersList",
					"pathName": "pages/payAndDelivery/ordersList/ordersList",
					"query": "disId=1",
					"scene": null
				},
				{
					"id": 3,
					"name": "pages/payAndDelivery/paymentPage/paymentPage",
					"pathName": "pages/payAndDelivery/paymentPage/paymentPage",
					"query": "nxOrdersId=1",
					"scene": null
				},
				{
					"id": -1,
					"name": "pages/pick/weightOrder/weightOrder",
					"pathName": "pages/pick/weightOrder/weightOrder",
					"query": "",
					"scene": null
				},
				{
					"id": -1,
					"name": "pagesCustomer/sign/sign",
					"pathName": "pagesCustomer/sign/sign",
					"query": "",
					"scene": null
				},
				{
					"id": -1,
					"name": "pagesCustomer/member/member",
					"pathName": "pagesCustomer/member/member",
					"query": "",
					"scene": null
				},
				{
					"id": -1,
					"name": "pagesCustomer/register/register",
					"pathName": "pagesCustomer/register/register",
					"query": "",
					"scene": null
				},
				{
					"id": -1,
					"name": "pagesCustomer/oftenOrder/oftenOrder",
					"pathName": "pagesCustomer/oftenOrder/oftenOrder",
					"query": "",
					"scene": null
				},
				{
					"id": -1,
					"name": "pagesCustomer/allOrders/allOrders",
					"pathName": "pagesCustomer/allOrders/allOrders",
					"query": "",
					"scene": null
				},
				{
					"id": -1,
					"name": "pages/pur/purGoods/purGoods",
					"pathName": "pages/pur/purGoods/purGoods",
					"query": "",
					"scene": null
				},
				{
					"id": -1,
					"name": "pages/prepare/goods/goods",
					"pathName": "pages/prepare/goods/goods",
					"query": "",
					"scene": null
				},
				{
					"id": -1,
					"name": "pages/payAndDelivery/deliveryBoyOrders/deliveryBoyOrders",
					"pathName": "pages/payAndDelivery/deliveryBoyOrders/deliveryBoyOrders",
					"query": "deliveryUserId=1",
					"scene": null
				},
				{
					"id": 14,
					"name": "pages/buy/buyPage/buyPage",
					"pathName": "pages/buy/buyPage/buyPage",
					"query": "",
					"scene": null
				},
				{
					"id": -1,
					"name": "pages/buy/purchaseGoods/purchaseGoods",
					"pathName": "pages/buy/purchaseGoods/purchaseGoods",
					"query": "purchaseUserId=1",
					"scene": null
				},
				{
					"id": -1,
					"name": "pagesCustomer/goodsPage/goodsPage",
					"pathName": "pagesCustomer/goodsPage/goodsPage",
					"query": "",
					"scene": null
				},
				{
					"id": 16,
					"name": "pagesCustomer/goodsPageDetail/goodsPageDetail",
					"pathName": "pagesCustomer/goodsPageDetail/goodsPageDetail",
					"query": "",
					"scene": null
				},
				{
					"id": -1,
					"name": "pagesCustomer/goodsMenu/goodsMenu",
					"pathName": "pagesCustomer/goodsMenu/goodsMenu",
					"query": "",
					"scene": null
				},
				{
					"id": -1,
					"name": "pagesCustomer/signTejia/signTejia",
					"pathName": "pagesCustomer/signTejia/signTejia",
					"query": "",
					"scene": null
				},
				{
					"id": -1,
					"name": "pagesCustomer/addTemplateItem/addTemplateItem",
					"pathName": "pagesCustomer/addTemplateItem/addTemplateItem",
					"query": "",
					"scene": null
				},
				{
					"id": 21,
					"name": "pagesCustomer/ordersDetailPage/ordersDetailPage",
					"pathName": "pagesCustomer/ordersDetailPage/ordersDetailPage",
					"query": "nxOrdersId=1",
					"scene": null
				},
				{
					"id": -1,
					"name": "pagesCustomer/caidiPage/caidiPage",
					"pathName": "pagesCustomer/caidiPage/caidiPage",
					"query": "",
					"scene": null
				},
				{
					"id": -1,
					"name": "pagesCustomer/userPage/userPage",
					"pathName": "pagesCustomer/userPage/userPage",
					"query": "",
					"scene": null
				},
				{
					"id": -1,
					"name": "pages/business/ibookCatalogue/ibookCatalogue",
					"pathName": "pages/business/ibookCatalogue/ibookCatalogue",
					"query": "",
					"scene": null
				},
				{
					"id": 24,
					"name": "pages/business/newStandard/newStandard",
					"pathName": "pages/business/newStandard/newStandard",
					"query": "",
					"scene": null
				},
				{
					"id": -1,
					"name": "pagesCustomer/customerInfo/customerInfo",
					"pathName": "pagesCustomer/customerInfo/customerInfo",
					"query": "",
					"scene": null
				},
				{
					"id": -1,
					"name": "pages/customer/addCustomer2/addCustomer2",
					"pathName": "pages/customer/addCustomer2/addCustomer2",
					"query": "",
					"scene": null
				},
				{
					"id": -1,
					"name": "pages/customer/addCustomer3/addCustomer3",
					"pathName": "pages/customer/addCustomer3/addCustomer3",
					"query": "",
					"scene": null
				},
				{
					"id": -1,
					"name": "pages/customer/addCustomer4/addCustomer4",
					"pathName": "pages/customer/addCustomer4/addCustomer4",
					"query": "",
					"scene": null
				},
				{
					"id": -1,
					"name": "pages/customer/addCustomer5/addCustomer5",
					"pathName": "pages/customer/addCustomer5/addCustomer5",
					"query": "",
					"scene": null
				},
				{
					"id": 30,
					"name": "pages/customer/addCustomer6/addCustomer6",
					"pathName": "pages/customer/addCustomer6/addCustomer6",
					"query": "",
					"scene": null
				},
				{
					"id": 31,
					"name": "pages/login/login",
					"pathName": "pages/login/login",
					"query": "",
					"scene": null
				},
				{
					"id": -1,
					"name": "pages/index/index",
					"pathName": "pages/index/index",
					"query": "",
					"scene": null
				},
				{
					"id": -1,
					"name": "pages/signe/dingSigne",
					"pathName": "pages/signe/dingSigne",
					"query": "",
					"scene": null
				},
				{
					"id": -1,
					"name": "pages/signe1/enterprisetype",
					"pathName": "pages/signe1/enterprisetype",
					"query": "",
					"scene": null
				},
				{
					"id": -1,
					"name": "pages/restaurant/myCode/myCode",
					"pathName": "pages/restaurant/myCode/myCode",
					"query": "",
					"scene": null
				},
				{
					"id": 36,
					"name": "pages/restaurant/stepOne/stepOne",
					"pathName": "pages/restaurant/stepOne/stepOne",
					"query": "id=24",
					"scene": null
				},
				{
					"id": -1,
					"name": "pages/restaurant/restaurantList/restaurantList",
					"pathName": "pages/restaurant/restaurantList/restaurantList",
					"query": "",
					"scene": null
				},
				{
					"id": -1,
					"name": "pagesPicker/pIndex/pIndex",
					"pathName": "pagesPicker/pIndex/pIndex",
					"query": "id=1",
					"scene": null
				},
				{
					"id": -1,
					"name": "pagesPicker/pSearchPrinter/pSearchPrinter",
					"pathName": "pagesPicker/pSearchPrinter/pSearchPrinter",
					"query": "",
					"scene": null
				},
				{
					"id": 40,
					"name": "pages/buy/sharePage/sharePage",
					"pathName": "pages/buy/sharePage/sharePage",
					"query": "batchId=10",
					"scene": null
				}
			]
		}
	}
}